aoirint_hg100rclient/__init__.py
aoirint_hg100rclient/client.py
aoirint_hg100rclient/config.py
aoirint_hg100rclient/script.py
aoirint_hg100rclient-20231018.2.dist-info/LICENSE
aoirint_hg100rclient-20231018.2.dist-info/METADATA
aoirint_hg100rclient-20231018.2.dist-info/WHEEL
aoirint_hg100rclient-20231018.2.dist-info/entry_points.txt
aoirint_hg100rclient-20231018.2.dist-info/top_level.txt
aoirint_hg100rclient-20231018.2.dist-info/RECORD
