Metadata-Version: 2.1
Name: aoirint-hg100rclient
Version: 20231018.2
Summary: CATV回線用モデムHUMAX HG100R-02JGをHTTP API経由で操作するための非公式パッケージ
Home-page: https://github.com/aoirint/aoirint_hg100rclient
Author: aoirint
Author-email: aoirint@gmail.com
Classifier: Development Status :: 3 - Alpha
Classifier: Programming Language :: Python
Classifier: Programming Language :: Python :: 3
Classifier: Programming Language :: Python :: 3.8
Classifier: Programming Language :: Python :: 3.9
Classifier: Programming Language :: Python :: 3.10
Classifier: Programming Language :: Python :: 3.11
License-File: LICENSE
Requires-Dist: requests
Requires-Dist: pydantic
